lumigo_core/VERSION
lumigo_core/__init__.py
lumigo_core/configuration.py
lumigo_core/logger.py
lumigo_core/lumigo_utils.py
lumigo_core/parsing_utils.py
lumigo_core/py.typed
lumigo_core/scrubbing.py
lumigo_core/libs/__init__.py
lumigo_core/libs/xmltodict.py
lumigo_core/triggers/__init__.py
lumigo_core/triggers/event_trigger.py
lumigo_core/triggers/trigger_parsing/__init__.py
lumigo_core/triggers/trigger_parsing/apigw_parser.py
lumigo_core/triggers/trigger_parsing/appsync_parser.py
lumigo_core/triggers/trigger_parsing/cloudwatch_parser.py
lumigo_core/triggers/trigger_parsing/dynamodb_parser.py
lumigo_core/triggers/trigger_parsing/event_trigger_base.py
lumigo_core/triggers/trigger_parsing/eventbridge_parser.py
lumigo_core/triggers/trigger_parsing/kafka_parser.py
lumigo_core/triggers/trigger_parsing/kinesis_parser.py
lumigo_core/triggers/trigger_parsing/load_balancer_parser.py
lumigo_core/triggers/trigger_parsing/s3_parser.py
lumigo_core/triggers/trigger_parsing/sns_parser.py
lumigo_core/triggers/trigger_parsing/sqs_parser.py
lumigo_core-0.0.16.dist-info/LICENSE
lumigo_core-0.0.16.dist-info/METADATA
lumigo_core-0.0.16.dist-info/WHEEL
lumigo_core-0.0.16.dist-info/top_level.txt
lumigo_core-0.0.16.dist-info/RECORD
