Metadata-Version: 2.1
Name: lumigo-core
Version: 0.0.16
Summary: Lumigo core utils
Home-page: https://github.com/lumigo-io/python-core.git
Author: Lumigo LTD (https://lumigo.io)
Author-email: support@lumigo.io
License: Apache License 2.0
Platform: UNKNOWN
Classifier: Programming Language :: Python :: 3
Classifier: Operating System :: OS Independent
